{
  "project_info": {
    "project_number": "632729438981",
    "project_id": "learning-d5f18",
    "storage_bucket": "learning-d5f18.appspot.com"
  },
  "client": [
    {
      "client_info": {
        "mobilesdk_app_id": "1:632729438981:android:29af94ca0fa011eeafc56c",
        "android_client_info": {
          "package_name": "com.example.android.eggtimernotifications"
        }
      },
      "oauth_client": [
        {
          "client_id": "632729438981-vfco1jik6gc93rnvd02f0c3it17qkeks.apps.googleusercontent.com",
          "client_type": 3
        }
      ],
      "api_key": [
        {
          "current_key": "AIzaSyDnFHmkpWe7t6vCZCStf5j1SPFZrTIc_00"
        }
      ],
      "services": {
        "appinvite_service": {
          "other_platform_oauth_client": [
            {
              "client_id": "632729438981-vfco1jik6gc93rnvd02f0c3it17qkeks.apps.googleusercontent.com",
              "client_type": 3
            }
          ]
        }
      }
    }
  ],
  "configuration_version": "1"
}